pumpia/__init__.py
pumpia/contrib/__init__.py
pumpia/contrib/example/__init__.py
pumpia/contrib/example/collection.py
pumpia/contrib/example/example.py
pumpia/contrib/example/module.py
pumpia/file_handling/__init__.py
pumpia/file_handling/dicom_structures.py
pumpia/file_handling/dicom_tags.py
pumpia/file_handling/general_structures.py
pumpia/file_handling/dicom_tags/CTTags.py
pumpia/file_handling/dicom_tags/DicomTags.py
pumpia/file_handling/dicom_tags/MRTags.py
pumpia/file_handling/dicom_tags/NucMedTags.py
pumpia/file_handling/dicom_tags/USTags.py
pumpia/file_handling/dicom_tags/XRAYTags.py
pumpia/file_handling/dicom_tags/__init__.py
pumpia/file_handling/dicom_tags/bases.py
pumpia/image_handling/__init__.py
pumpia/image_handling/image_structures.py
pumpia/image_handling/image_validators.py
pumpia/image_handling/roi_structures.py
pumpia/module_handling/__init__.py
pumpia/module_handling/context.py
pumpia/module_handling/manager.py
pumpia/module_handling/module_collections.py
pumpia/module_handling/modules.py
pumpia/module_handling/in_outs/__init__.py
pumpia/module_handling/in_outs/groups.py
pumpia/module_handling/in_outs/roi_ios.py
pumpia/module_handling/in_outs/simple.py
pumpia/module_handling/in_outs/viewer_ios.py
pumpia/utilities/__init__.py
pumpia/utilities/array_utils.py
pumpia/utilities/dicom_utils.py
pumpia/utilities/feature_utils.py
pumpia/utilities/file_utils.py
pumpia/utilities/string_validators.py
pumpia/utilities/tkinter_utils.py
pumpia/utilities/typing.py
pumpia/widgets/__init__.py
pumpia/widgets/context_managers.py
pumpia/widgets/entry_boxes.py
pumpia/widgets/scrolled_window.py
pumpia/widgets/tables.py
pumpia/widgets/typing.py
pumpia/widgets/variables.py
pumpia/widgets/viewers.py
pumpia-0.5.16.dist-info/METADATA
pumpia-0.5.16.dist-info/WHEEL
pumpia-0.5.16.dist-info/licenses/LICENSE
pumpia-0.5.16.dist-info/RECORD
