Metadata-Version: 2.4
Name: pumpia
Version: 0.5.16
Summary: A simple to use framework for making user interfaces for image analysis.
Project-URL: Homepage, https://principle-five.github.io/pumpia/index.html
Project-URL: Source, https://github.com/Principle-Five/PumpIA
Project-URL: Issues, https://github.com/Principle-Five/PumpIA/issues
Author: Zack Ravetz et al.
License-Expression: BSD-3-Clause
License-File: LICENSE
Classifier: Intended Audience :: Science/Research
Classifier: License :: OSI Approved :: BSD License
Classifier: Programming Language :: Python :: 3
Classifier: Programming Language :: Python :: 3 :: Only
Classifier: Programming Language :: Python :: 3.12
Classifier: Programming Language :: Python :: 3.13
Classifier: Topic :: Scientific/Engineering
Classifier: Topic :: Scientific/Engineering :: Image Processing
Classifier: Topic :: Software Development
Requires-Python: >=3.12
Requires-Dist: matplotlib==3.*
Requires-Dist: numpy==2.*
Requires-Dist: pillow==11.*
Requires-Dist: pydicom==3.*
Requires-Dist: scipy==1.*
Provides-Extra: docs
Requires-Dist: sphinx; extra == 'docs'
Requires-Dist: sphinx-rtd-theme; extra == 'docs'
